gapSolutions_client/__init__.py
gapSolutions_client/config.py
gapSolutions_client/constants.py
gapSolutions_client/logger.py
gapSolutions_client/test.py
gapSolutions_client/utils.py
gapSolutions_client/account/__init__.py
gapSolutions_client/account/account.py
gapSolutions_client/account/account_type.py
gapSolutions_client/file/__init__.py
gapSolutions_client/file/file.py
gapSolutions_client/file/file_type.py
gapSolutions_client/folder/__init__.py
gapSolutions_client/folder/folder.py
gapSolutions_client/folder/folder_type.py
gapSolutions_client/test_account/__init__.py
gapSolutions_client/test_account/test_account.py
gapSolutions_client/test_account/test_account_type.py
gapSolutions_client/test_file/__init__.py
gapSolutions_client/test_file/test_file.py
gapSolutions_client/test_file/test_file_type.py
gapSolutions_client/test_folder/__init__.py
gapSolutions_client/test_folder/test_folder.py
gapSolutions_client/test_folder/test_folder_type.py
gapSolutions_client-0.1.30.dist-info/METADATA
gapSolutions_client-0.1.30.dist-info/WHEEL
gapSolutions_client-0.1.30.dist-info/top_level.txt
gapSolutions_client-0.1.30.dist-info/RECORD
