Metadata-Version: 2.1
Name: gapSolutions-client
Version: 0.1.30
Summary: gapSolutions client package
Home-page: https://bitbucket.org/designoptics/api-python-wrapper/src/master/
Author: Samer Hisham
Author-email: samerrhisham@gmail.com
Keywords: python,gapSolutions
Classifier: Development Status :: 3 - Alpha
Classifier: Intended Audience :: Education
Classifier: Programming Language :: Python :: 3
Classifier: Operating System :: MacOS :: MacOS X
Classifier: Operating System :: Microsoft :: Windows
Requires-Dist: requests
Requires-Dist: python-dateutil
